bossman/__init__.py
bossman/abc.py
bossman/cache.py
bossman/config.py
bossman/errors.py
bossman/logging.py
bossman/migrations.py
bossman/repo.py
bossman/resources.py
bossman/rich.py
bossman/cli/__init__.py
bossman/cli/apply_cmd.py
bossman/cli/init_cmd.py
bossman/cli/log_cmd.py
bossman/cli/release_cmd.py
bossman/cli/status_cmd.py
bossman/cli/validate_cmd.py
bossman/plugins/__init__.py
bossman/plugins/akamai/__init__.py
bossman/plugins/akamai/edgehostname.py
bossman/plugins/akamai/property.py
bossman/plugins/akamai/utils.py
bossman/plugins/akamai/cloudlet_v3/__init__.py
bossman/plugins/akamai/cloudlet_v3/client.py
bossman/plugins/akamai/cloudlet_v3/data.py
bossman/plugins/akamai/cloudlet_v3/error.py
bossman/plugins/akamai/cloudlet_v3/resource.py
bossman/plugins/akamai/cloudlet_v3/resourcetype.py
bossman/plugins/akamai/cloudlet_v3/schema.py
bossman/plugins/akamai/cloudlet_v3/test.py
bossman/plugins/akamai/cloudlet_v3/ui.py
bossman/plugins/akamai/cloudlet_v3/schemas/match-rules.json
bossman/plugins/akamai/cloudlet_v3/schemas/match_rule-AS-1.0.json
bossman/plugins/akamai/cloudlet_v3/schemas/match_rule-ER-1.0.json
bossman/plugins/akamai/cloudlet_v3/schemas/match_rule-FR-1.0.json
bossman/plugins/akamai/cloudlet_v3/schemas/update-policy-version.json
bossman/plugins/akamai/lib/__init__.py
bossman/plugins/akamai/lib/edgegrid.py
bossman/plugins/akamai/lib/hapi.py
bossman/plugins/akamai/lib/papi.py
bossman-0.49.0.dist-info/licenses/LICENSE.txt
bossman-0.49.0.dist-info/METADATA
bossman-0.49.0.dist-info/WHEEL
bossman-0.49.0.dist-info/entry_points.txt
bossman-0.49.0.dist-info/top_level.txt
bossman-0.49.0.dist-info/RECORD
